powerball_quantum/__init__.py
powerball_quantum/__main__.py
powerball_quantum/cli.py
powerball_quantum/powerball_data.csv
powerball_quantum/predictor.py
powerball_quantum-1.0.2.dist-info/licenses/LICENSE
powerball_quantum-1.0.2.dist-info/METADATA
powerball_quantum-1.0.2.dist-info/WHEEL
powerball_quantum-1.0.2.dist-info/entry_points.txt
powerball_quantum-1.0.2.dist-info/top_level.txt
powerball_quantum-1.0.2.dist-info/RECORD
