Metadata-Version: 2.4
Name: powerball-quantum
Version: 1.0.2
Summary: Powerball number predictor using quantum-inspired algorithm with momentum, mean reversion, and statistical filters
Author-email: seochan99 <gmlcks00513@gmail.com>
License: MIT
Project-URL: Homepage, https://github.com/seochan99/powerball-quantum
Project-URL: Repository, https://github.com/seochan99/powerball-quantum
Project-URL: Issues, https://github.com/seochan99/powerball-quantum/issues
Keywords: powerball,lottery,predictor,quantum,statistics,probability
Classifier: Development Status :: 4 - Beta
Classifier: Intended Audience :: End Users/Desktop
Classifier: License :: OSI Approved :: MIT License
Classifier: Operating System :: OS Independent
Classifier: Programming Language :: Python :: 3
Classifier: Programming Language :: Python :: 3.8
Classifier: Programming Language :: Python :: 3.9
Classifier: Programming Language :: Python :: 3.10
Classifier: Programming Language :: Python :: 3.11
Classifier: Programming Language :: Python :: 3.12
Classifier: Topic :: Games/Entertainment
Requires-Python: >=3.8
License-File: LICENSE
Requires-Dist: pandas>=1.3.0
Requires-Dist: requests>=2.25.0
Dynamic: license-file
